gpt_suite/__init__.py
gpt_suite/gpt_mp_handler.py
gpt_suite/gpt_util.py
gpt_suite-0.3.6.dist-info/LICENSE
gpt_suite-0.3.6.dist-info/METADATA
gpt_suite-0.3.6.dist-info/WHEEL
gpt_suite-0.3.6.dist-info/top_level.txt
gpt_suite-0.3.6.dist-info/RECORD
