Metadata-Version: 2.1
Name: gpt_suite
Version: 0.3.6
Summary: A Suite for Querying ChatGPT
Author-email: Chengfei Wu <wucf@projp.org>
License: MIT
Project-URL: homepage, https://github.com/dreamilization/gpt-suite
Classifier: Programming Language :: Python :: 3
Classifier: License :: OSI Approved :: MIT License
Classifier: Operating System :: OS Independent
Requires-Python: >=3.8
License-File: LICENSE
Requires-Dist: openai <2,>=1.34.0
Requires-Dist: tqdm >=4.66.1
